{
    "list":[
        {
           "img":"https://kaola-haitao.oss.kaolacdn.com/be97e628-df3a-4b31-82ee-edf3686883d2T1907021531_192_220.png?x-oss-process=image/resize,w_192,h_220/quality,q_95"
        },
        {

            "img":"https://kaola-haitao.oss.kaolacdn.com/5ee97ce7-9c93-4f79-8ca5-1a1de0cc85afT1907021609_192_220.png?x-oss-process=image/resize,w_192,h_220/quality,q_95"
         },
         {

            "img":"https://kaola-haitao.oss.kaolacdn.com/7309e72f-1c23-424a-a220-91badfa2f49eT1907021955_192_220.png?x-oss-process=image/resize,w_192,h_220/quality,q_95"
         },
         {
          
            "img":"https://kaola-haitao.oss.kaolacdn.com/f59ffba8-c2ad-457c-9070-7f4a8e5b83b7T1907021534_192_220.png?x-oss-process=image/resize,w_192,h_220/quality,q_95"
         },
         {
           
            "img":"https://kaola-haitao.oss.kaolacdn.com/ba7064d2-37e7-4505-b3fd-93602df85b25T1902210142_192_220.png?x-oss-process=image/resize,w_192,h_220/quality,q_95"
         },
         {
           
            "img":"https://kaola-haitao.oss.kaolacdn.com/eb5afb31-3c18-4331-b5bb-f03b4b04040aT1911061954_192_220.png?x-oss-process=image/resize,w_192,h_220/quality,q_95"
         },
         {
          
            "img":"https://kaola-haitao.oss.kaolacdn.com/038bb478-de11-4335-8bba-452f1762c0bbT2003271652_192_220.jpg?x-oss-process=image/resize,w_192,h_220/quality,q_95/format,webp"
         },
         {
         
            "img":"https://kaola-haitao.oss.kaolacdn.com/1914d008-312b-4410-a917-f6413fe84566T19062601008_192_220.png?x-oss-process=image/resize,w_192,h_220/quality,q_95"
         },
         {
          
            "img":"https://kaola-haitao.oss.kaolacdn.com/fee4bf4d-1a1a-4ff6-95e1-7cfd497cb3afT1907111605_192_220.png?x-oss-process=image/resize,w_192,h_220/quality,q_95"
         },
         {
            "img":"https://kaola-haitao.oss.kaolacdn.com/7b848599-d340-4c12-8912-7618f492b8e7T19010151358_192_220.png?x-oss-process=image/resize,w_192,h_220/quality,q_95"
         }
      ],
         "recItems": [
            {
      "recType": 22,
      "countryLogo": "http://kaola-haitao.oss.kaolacdn.com/c0be3e6c11de4adb9ea90df712da9aea1419662386933i46mbwfo10003.png",
      "linkUrl": "https://m-goods.kaola.com/product/2859422.html",
      "goodsImage": "http://kaola-haitao.oss.kaolacdn.com/a0601a17c8e342c09285a6208e48a5fd_800_800.jpg",
      "goodsImage1":"https://kaola-haitao.oss.kaolacdn.com/c4f57003c8e84664bad4c9d174ae4b401562655122322jxvgih6k10122.jpg?x-oss-process=image/resize,w_750,h_0/quality,q_75/format,webp",
      "scm": "v1.1008.1008_p_2859422.234618_234266_91519.cate_106177-cts_1599708057069-channel_2-fccrowds_ul-pinleici_面膜-match&udl;score_1&doot;0-bucketid_null-abid_183397-trigger&udl;weight_null-content&udl;type_1-pvid_0c2824d7#9ffe#4dc2#bcdf#0d92c6f7f54c-price_36&doot;0-pageno_1-appid_18806-match&udl;type_21-position_0-brand_6307-expid_null",
      "goodsName": "【仅限9.9-9.11】韩国",
      "goodMinName":"JMsolution面膜燕窝水母蜗牛蜂蜜急救珍珠面膜夏季保湿补水【不支持备注下单】",
      "realTimeRec": false,
      "titleForeHeadLabelList": [
      ],
      "contrastPriceInfo": {
      "contrastPrice": "33",
      "priceType": 4
      },
      "labelListWithStyle": [
      {
      "styleCode": 202,
      "content": "满2件减24"
      },
      {
      "styleCode": 202,
      "content": "特价"
      }
      ],
      "enjoyPriceInfo": {
      "enjoyPrice": "36",
      "priceType": 0
      },
      "countryName": "JMsolution",
      "template": {
      "name": "kl_feed_goods",
      "version": "7",
      "url": "https://ossgw.alicdn.com/rapid-oss-bucket/1599199439687/kl_feed_goods.zip"
      },
      "goodsId": 2859422,
      "categoryName": "贴片面膜",
      "imageUrl": "http://kaola-pop.oss.kaolacdn.com/7f646cb4cebc4974a44f39121b05f689_800_800.jpg",
      "trackInfo": {
      "utScm": "20140737.p_2859422.234618_234266_91519.cate_106177-cts_1599708057070-channel_2-fccrowds_ul-bucketid_null-contenttype_1-matchscore_10000-pvid_0c2824d7#9ffe#4dc2#bcdf#0d92c6f7f54c-price_360000-pageno_1-appid_18806-matchtype_21-triggerweight_null-position_0-brand_6307-expid_null",
      "utLogMap": {
      "sr_price": "36.0",
      "sr_abid": "183397",
      "sr_trigger": "null",
      "sr_brand": "6307",
      "sr_pos": "0",
      "sr_appid": "18806",
      "sr_rank_score": "null",
      "mtx_exp": "null",
      "sr_cvr": "null",
      "sr_ctt_type": "null",
      "sr_match_type": "21",
      "sr_recall_score": "null",
      "mtx_crowds": "null",
      "sr_t_at": "null",
      "sr_object_type": "p",
      "sr_t_td": "null",
      "sr_scene": "2",
      "sr_match_score": "1.0",
      "sr_pvid": "0c2824d7#9ffe#4dc2#bcdf#0d92c6f7f54c",
      "mtx_bucket": "null",
      "sr_object_id": "2859422",
      "sr_ctt_goods": "null",
      "sr_pageno": "1",
      "sr_trigger_w": "null",
      "sr_cate": "106177",
      "sr_ctr": "null",
      "sr_tc_ctr": "null",
      "sr_final_score": "null",
      "sr_tc_clk": "null",
      "sr_tc_td": "null",
      "sr_pinleici": "面膜"
      }
      },
      "currentPrice": 36.00,
      "vip" :32,
      "similarLinkUrl": "http://m.kaola.com/klapp?klpn=similarGoodsPage&goods_id=2859422",
      "showFeed": false
      },
      {
      "recType": 22,
      "countryLogo": "http://kaola-haitao.oss.kaolacdn.com/1077833fa2854dcb97502084f24f449d1419659976324i46kw8bh10001.png",
      "linkUrl": "https://m-goods.kaola.com/product/2891970.html",
      "goodsImage": "http://kaola-haitao.oss.kaolacdn.com/22308a215249408096a572b9b9c06b4b_800_800.jpg",
      "goodsImage1":"https://kaola-haitao.oss.kaolacdn.com/a3e141b464eb4dc29414ec323f45f1621596103616831D5F41C68BBB9A08D9B2146E698F6AEEA.jpg?x-oss-process=image/resize,w_750,h_0/quality,q_75/format,webp",
      "scm": "v1.1008.1008_p_2891970.234618_234266_91519.cate_736-cts_1599708057070-channel_2-fccrowds_ul-pinleici_唇膏-match&udl;score_0&doot;9054-bucketid_null-abid_183397-trigger&udl;weight_null-content&udl;type_1-pvid_0c2824d7#9ffe#4dc2#bcdf#0d92c6f7f54c-price_95&doot;0-pageno_1-appid_18806-match&udl;type_21-position_1-brand_4291-expid_null",
      "goodsName": "【张艺兴同款】【经典小辣",
      "goodMinName":"椒】MAC魅可 子弹头时尚唇膏 chili复古红气质牛血色 新品尤雾弹",
      "realTimeRec": false,
      "titleForeHeadLabelList": [
      "https://kaola-haitao.oss.kaolacdn.com/e37aaf47-b4e4-4602-8309-5edf8a2300f8T2008031346_78_39.png?klsize=78x39"
      ],
      "contrastPriceInfo": {
      "contrastPrice": "89",
      "priceType": 4
      },
      "labelListWithStyle": [
      {
      "styleCode": 202,
      "content": "豆抵0.5元"
      },
      {
      "styleCode": 202,
      "content": "特价"
      }
      ],
      "enjoyPriceInfo": {
      "enjoyPrice": "95",
      "priceType": 0
      },
      "countryName": "魅可",
      "template": {
      "name": "kl_feed_goods",
      "version": "7",
      "url": "https://ossgw.alicdn.com/rapid-oss-bucket/1599199439687/kl_feed_goods.zip"
      },
      "goodsId": 2891970,
      "categoryName": "唇膏/口红",
      "imageUrl": "http://kaola-haitao.oss.kaolacdn.com/feb488bd587b4cc594ee0daffd14a3ec1596103616784FFD411D88973D68E127A29E66C288678.jpg",
      "trackInfo": {
      "utScm": "20140737.p_2891970.234618_234266_91519.cate_736-cts_1599708057070-channel_2-fccrowds_ul-bucketid_null-contenttype_1-matchscore_9054-pvid_0c2824d7#9ffe#4dc2#bcdf#0d92c6f7f54c-price_950000-pageno_1-appid_18806-matchtype_21-triggerweight_null-position_1-brand_4291-expid_null",
      "utLogMap": {
      "sr_price": "95.0",
      "sr_abid": "183397",
      "sr_trigger": "null",
      "sr_brand": "4291",
      "sr_pos": "1",
      "sr_appid": "18806",
      "sr_rank_score": "null",
      "mtx_exp": "null",
      "sr_cvr": "null",
      "sr_ctt_type": "null",
      "sr_match_type": "21",
      "sr_recall_score": "null",
      "mtx_crowds": "null",
      "sr_t_at": "null",
      "sr_object_type": "p",
      "sr_t_td": "null",
      "sr_scene": "2",
      "sr_match_score": "0.9054",
      "sr_pvid": "0c2824d7#9ffe#4dc2#bcdf#0d92c6f7f54c",
      "mtx_bucket": "null",
      "sr_object_id": "2891970",
      "sr_ctt_goods": "null",
      "sr_pageno": "1",
      "sr_trigger_w": "null",
      "sr_cate": "736",
      "sr_ctr": "null",
      "sr_tc_ctr": "null",
      "sr_final_score": "null",
      "sr_tc_clk": "null",
      "sr_tc_td": "null",
      "sr_pinleici": "唇膏"
      }
      },
      "currentPrice": 95.00,
      "vip" :80,
      "similarLinkUrl": "http://m.kaola.com/klapp?klpn=similarGoodsPage&goods_id=2891970",
      "showFeed": false
      },
      {
      "recType": 22,
      "countryLogo": "http://kaola-haitao.oss.kaolacdn.com/d3c18d60f0e54c32af5cf24d18be585b1419662519909i46mer1g10007.png",
      "linkUrl": "https://m-goods.kaola.com/product/6023174.html",
      "goodsImage": "http://kaola-haitao.oss.kaolacdn.com/c54e2990e328489d88611907ee7c949e_800_800.jpg",
      "goodsImage1":"https://kaola-haitao.oss.kaolacdn.com/981f3054f58342e18778949e21bbe5f21576465832376k47v1x9j10770.jpg?x-oss-process=image/resize,w_750,h_0/quality,q_75/format,webp",
      "scm": "v1.1008.1008_p_6023174.234618_234266_91519.cate_736-cts_1599708057070-channel_2-fccrowds_ul-pinleici_-match&udl;score_0&doot;7291-bucketid_null-abid_183397-trigger&udl;weight_null-content&udl;type_1-pvid_0c2824d7#9ffe#4dc2#bcdf#0d92c6f7f54c-price_169&doot;0-pageno_1-appid_18806-match&udl;type_21-position_2-brand_1454-expid_null",
      "goodsName": "Dior 迪奥 新烈艳蓝金唇膏 ",
      "goodMinName":"3.5克 必备经典 气场满分",
      "realTimeRec": false,
      "titleForeHeadLabelList": [
      "https://kaola-haitao.oss.kaolacdn.com/e37aaf47-b4e4-4602-8309-5edf8a2300f8T2008031346_78_39.png?klsize=78x39"
      ],
      "contrastPriceInfo": {
      "contrastPrice": "159",
      "priceType": 4
      },
      "labelListWithStyle": [
      {
      "styleCode": 202,
      "content": "豆抵0.5元"
      },
      {
      "styleCode": 202,
      "content": "新人价"
      }
      ],
      "enjoyPriceInfo": {
      "enjoyPrice": "169",
      "priceType": 0
      },
      "countryName": "迪奥",
      "template": {
      "name": "kl_feed_goods",
      "version": "7",
      "url": "https://ossgw.alicdn.com/rapid-oss-bucket/1599199439687/kl_feed_goods.zip"
      },
      "goodsId": 6023174,
      "categoryName": "唇膏/口红",
      "imageUrl": "http://kaola-haitao.oss.kaolacdn.com/95e8b520b2d0452b8e302fda525cd0011576465777139k47v0qn611287.jpg",
      "trackInfo": {
      "utScm": "20140737.p_6023174.234618_234266_91519.cate_736-cts_1599708057070-channel_2-fccrowds_ul-bucketid_null-contenttype_1-matchscore_7291-pvid_0c2824d7#9ffe#4dc2#bcdf#0d92c6f7f54c-price_1690000-pageno_1-appid_18806-matchtype_21-triggerweight_null-position_2-brand_1454-expid_null",
      "utLogMap": {
      "sr_price": "169.0",
      "sr_abid": "183397",
      "sr_trigger": "null",
      "sr_brand": "1454",
      "sr_pos": "2",
      "sr_appid": "18806",
      "sr_rank_score": "null",
      "mtx_exp": "null",
      "sr_cvr": "null",
      "sr_ctt_type": "null",
      "sr_match_type": "21",
      "sr_recall_score": "null",
      "mtx_crowds": "null",
      "sr_t_at": "null",
      "sr_object_type": "p",
      "sr_t_td": "null",
      "sr_scene": "2",
      "sr_match_score": "0.7291",
      "sr_pvid": "0c2824d7#9ffe#4dc2#bcdf#0d92c6f7f54c",
      "mtx_bucket": "null",
      "sr_object_id": "6023174",
      "sr_ctt_goods": "null",
      "sr_pageno": "1",
      "sr_trigger_w": "null",
      "sr_cate": "736",
      "sr_ctr": "null",
      "sr_tc_ctr": "null",
      "sr_final_score": "null",
      "sr_tc_clk": "null",
      "sr_tc_td": "null",
      "sr_pinleici": ""
      }
      },
      "currentPrice": 169.00,
      "vip" :156,
      "similarLinkUrl": "http://m.kaola.com/klapp?klpn=similarGoodsPage&goods_id=6023174",
      "showFeed": false
      },
      {
      "recType": 22,
      "countryLogo": "http://kaola-haitao.oss.kaolacdn.com/1077833fa2854dcb97502084f24f449d1419659976324i46kw8bh10001.png",
      "linkUrl": "https://m-goods.kaola.com/product/90884.html",
      "goodsImage": "http://kaola-haitao.oss.kaolacdn.com/221afc28b3bc49ba92d17a24830f4df3_800_800.jpg",
      "goodsImage1":"https://kaola-haitao.oss.kaolacdn.com/4244c80e3d0e465194a66ac9b56d384d_800_800.jpg?x-oss-process=image/resize,w_262,h_262/quality,q_90",
      "scm": "v1.1008.1008_p_6023174.234618_234266_91519.cate_736-cts_1599708057070-channel_2-fccrowds_ul-pinleici_-match&udl;score_0&doot;7291-bucketid_null-abid_183397-trigger&udl;weight_null-content&udl;type_1-pvid_0c2824d7#9ffe#4dc2#bcdf#0d92c6f7f54c-price_169&doot;0-pageno_1-appid_18806-match&udl;type_21-position_2-brand_1454-expid_null",
      "scm": "v1.1008.1008_p_90884.234618_234266_91519.cate_111055-cts_1599708057070-channel_2-fccrowds_ul-pinleici_精华-match&udl;score_0&doot;6871-bucketid_null-abid_183397-trigger&udl;weight_null-content&udl;type_1-pvid_0c2824d7#9ffe#4dc2#bcdf#0d92c6f7f54c-price_499&doot;0-pageno_1-appid_18806-match&udl;type_21-position_3-brand_1566-expid_null",
      "goodsName": "ESTĒE LAUDER 雅诗兰黛小",
      "goodMinName":"棕瓶面部精华 特润修护肌透精华露 50毫升",
      "realTimeRec": false,
      "titleForeHeadLabelList": [
      "https://kaola-haitao.oss.kaolacdn.com/e37aaf47-b4e4-4602-8309-5edf8a2300f8T2008031346_78_39.png?klsize=78x39"
      ],
      "contrastPriceInfo": {
      "contrastPrice": "479",
      "priceType": 4
      },
      "labelListWithStyle": [
      {
      "styleCode": 202,
      "content": "特价"
      },
      {
      "styleCode": 300,
      "content": "包税"
      }
      ],
      "enjoyPriceInfo": {
      "enjoyPrice": "499",
      "priceType": 0
      },
      "countryName": "雅诗兰黛",
      "template": {
      "name": "kl_feed_goods",
      "version": "7",
      "url": "https://ossgw.alicdn.com/rapid-oss-bucket/1599199439687/kl_feed_goods.zip"
      },
      "goodsId": 90884,
      "categoryName": "液态精华",
      "imageUrl": "http://kaola-haitao.oss.kaolacdn.com/750a37a464b545ca85c555c88b0e93ab158710741859508C0CF3290A4B8B7A523781980CB3ADB.jpg",
      "trackInfo": {
      "utScm": "20140737.p_90884.234618_234266_91519.cate_111055-cts_1599708057070-channel_2-fccrowds_ul-bucketid_null-contenttype_1-matchscore_6871-pvid_0c2824d7#9ffe#4dc2#bcdf#0d92c6f7f54c-price_4990000-pageno_1-appid_18806-matchtype_21-triggerweight_null-position_3-brand_1566-expid_null",
      "utLogMap": {
      "sr_price": "499.0",
      "sr_abid": "183397",
      "sr_trigger": "null",
      "sr_brand": "1566",
      "sr_pos": "3",
      "sr_appid": "18806",
      "sr_rank_score": "null",
      "mtx_exp": "null",
      "sr_cvr": "null",
      "sr_ctt_type": "null",
      "sr_match_type": "21",
      "sr_recall_score": "null",
      "mtx_crowds": "null",
      "sr_t_at": "null",
      "sr_object_type": "p",
      "sr_t_td": "null",
      "sr_scene": "2",
      "sr_match_score": "0.6871",
      "sr_pvid": "0c2824d7#9ffe#4dc2#bcdf#0d92c6f7f54c",
      "mtx_bucket": "null",
      "sr_object_id": "90884",
      "sr_ctt_goods": "null",
      "sr_pageno": "1",
      "sr_trigger_w": "null",
      "sr_cate": "111055",
      "sr_ctr": "null",
      "sr_tc_ctr": "null",
      "sr_final_score": "null",
      "sr_tc_clk": "null",
      "sr_tc_td": "null",
      "sr_pinleici": "精华"
      }
      },
      "currentPrice": 499.00,
      "vip" :388,
      "similarLinkUrl": "http://m.kaola.com/klapp?klpn=similarGoodsPage&goods_id=90884",
      "showFeed": false
      },
      {
      "recType": 22,
      "countryLogo": "http://kaola-haitao.oss.kaolacdn.com/c0be3e6c11de4adb9ea90df712da9aea1419662386933i46mbwfo10003.png",
      "linkUrl": "https://m-goods.kaola.com/product/2132823.html",
      "goodsImage": "http://kaola-haitao.oss.kaolacdn.com/1aebed8d1a8448209bc291305530edbe_800_800.jpg",
      "goodsImage1":"https://kaola-pop.oss.kaolacdn.com/fb7389a2e919463b98ea9885c5736b0a_800_800.jpg?x-oss-process=image/resize,w_262,h_262/quality,q_90",
      "scm": "v1.1008.1008_p_2132823.234618_234266_91519.cate_726-cts_1599708057070-channel_2-fccrowds_ul-pinleici_隔离-match&udl;score_0&doot;6871-bucketid_null-abid_183397-trigger&udl;weight_null-content&udl;type_1-pvid_0c2824d7#9ffe#4dc2#bcdf#0d92c6f7f54c-price_119&doot;0-pageno_1-appid_18806-match&udl;type_21-position_4-brand_2397-expid_null",
      "goodsName": "【修颜提亮】LΛNEIGE 兰芝",
      "goodMinName":"雪纱丝柔防晒新款隔离霜 30毫升",
      "realTimeRec": false,
      "titleForeHeadLabelList": [
      "https://kaola-haitao.oss.kaolacdn.com/e37aaf47-b4e4-4602-8309-5edf8a2300f8T2008031346_78_39.png?klsize=78x39"
      ],
      "contrastPriceInfo": {
      "contrastPrice": "113",
      "priceType": 4
      },
      "labelListWithStyle": [
      {
      "styleCode": 202,
      "content": "特价"
      },
      {
      "styleCode": 300,
      "content": "包税"
      }
      ],
      "enjoyPriceInfo": {
      "enjoyPrice": "119",
      "priceType": 0
      },
      "countryName": "兰芝",
      "template": {
      "name": "kl_feed_goods",
      "version": "7",
      "url": "https://ossgw.alicdn.com/rapid-oss-bucket/1599199439687/kl_feed_goods.zip"
      },
      "goodsId": 2132823,
      "categoryName": "妆前/隔离",
      "imageUrl": "http://kaola-haitao.oss.kaolacdn.com/43596309d51144a6b0846215c1ce379615959066421925A3A69EFFDD5A2D62419F871F58818F3.jpg",
      "trackInfo": {
      "utScm": "20140737.p_2132823.234618_234266_91519.cate_726-cts_1599708057070-channel_2-fccrowds_ul-bucketid_null-contenttype_1-matchscore_6871-pvid_0c2824d7#9ffe#4dc2#bcdf#0d92c6f7f54c-price_1190000-pageno_1-appid_18806-matchtype_21-triggerweight_null-position_4-brand_2397-expid_null",
      "utLogMap": {
      "sr_price": "119.0",
      "sr_abid": "183397",
      "sr_trigger": "null",
      "sr_brand": "2397",
      "sr_pos": "4",
      "sr_appid": "18806",
      "sr_rank_score": "null",
      "mtx_exp": "null",
      "sr_cvr": "null",
      "sr_ctt_type": "null",
      "sr_match_type": "21",
      "sr_recall_score": "null",
      "mtx_crowds": "null",
      "sr_t_at": "null",
      "sr_object_type": "p",
      "sr_t_td": "null",
      "sr_scene": "2",
      "sr_match_score": "0.6871",
      "sr_pvid": "0c2824d7#9ffe#4dc2#bcdf#0d92c6f7f54c",
      "mtx_bucket": "null",
      "sr_object_id": "2132823",
      "sr_ctt_goods": "null",
      "sr_pageno": "1",
      "sr_trigger_w": "null",
      "sr_cate": "726",
      "sr_ctr": "null",
      "sr_tc_ctr": "null",
      "sr_final_score": "null",
      "sr_tc_clk": "null",
      "sr_tc_td": "null",
      "sr_pinleici": "隔离"
      }
      },
      "currentPrice": 119.00,
      "vip" :105,
      "similarLinkUrl": "http://m.kaola.com/klapp?klpn=similarGoodsPage&goods_id=2132823",
      "showFeed": false
      },
      {
      "recType": 22,
      "countryLogo": "http://kaola-haitao.oss.kaolacdn.com/d3c18d60f0e54c32af5cf24d18be585b1419662519909i46mer1g10007.png",
      "linkUrl": "https://m-goods.kaola.com/product/5654537.html",
      "goodsImage": "http://kaola-haitao.oss.kaolacdn.com/dc91cb935abb4c279cafeda4186a4530_800_800.jpg",
      "goodsImage1":"https://kaola-pop.oss.kaolacdn.com/0c2a02e00ada46889a8503a86aff3eb5_800_800.jpg?x-oss-process=image/resize,w_430/quality,q_85",
      "scm": "v1.1008.1008_p_5654537.234618_234266_91519.cate_736-cts_1599708057070-channel_2-fccrowds_ul-pinleici_唇膏-match&udl;score_0&doot;6861-bucketid_null-abid_183397-trigger&udl;weight_null-content&udl;type_1-pvid_0c2824d7#9ffe#4dc2#bcdf#0d92c6f7f54c-price_139&doot;0-pageno_1-appid_18806-match&udl;type_21-position_5-brand_1336-expid_null",
      "goodsName": "【YSL小金条】YSL 圣罗兰 ",
      "goodMinName":"雾面哑光细管口红 气质调 超显白",
      "realTimeRec": false,
      "titleForeHeadLabelList": [
      "https://kaola-haitao.oss.kaolacdn.com/e37aaf47-b4e4-4602-8309-5edf8a2300f8T2008031346_78_39.png?klsize=78x39"
      ],
      "contrastPriceInfo": {
      "contrastPrice": "132",
      "priceType": 4
      },
      "labelListWithStyle": [
      {
      "styleCode": 202,
      "content": "豆抵0.5元"
      },
      {
      "styleCode": 202,
      "content": "特价"
      }
      ],
      "enjoyPriceInfo": {
      "enjoyPrice": "139",
      "priceType": 0
      },
      "countryName": "圣罗兰",
      "template": {
      "name": "kl_feed_goods",
      "version": "7",
      "url": "https://ossgw.alicdn.com/rapid-oss-bucket/1599199439687/kl_feed_goods.zip"
      },
      "goodsId": 5654537,
      "categoryName": "唇膏/口红",
      "imageUrl": "http://kaola-haitao.oss.kaolacdn.com/249b7012d442441890198d9682f934d51575874119034k3y2rgbp10205.jpg",
      "trackInfo": {
      "utScm": "20140737.p_5654537.234618_234266_91519.cate_736-cts_1599708057070-channel_2-fccrowds_ul-bucketid_null-contenttype_1-matchscore_6861-pvid_0c2824d7#9ffe#4dc2#bcdf#0d92c6f7f54c-price_1390000-pageno_1-appid_18806-matchtype_21-triggerweight_null-position_5-brand_1336-expid_null",
      "utLogMap": {
      "sr_price": "139.0",
      "sr_abid": "183397",
      "sr_trigger": "null",
      "sr_brand": "1336",
      "sr_pos": "5",
      "sr_appid": "18806",
      "sr_rank_score": "null",
      "mtx_exp": "null",
      "sr_cvr": "null",
      "sr_ctt_type": "null",
      "sr_match_type": "21",
      "sr_recall_score": "null",
      "mtx_crowds": "null",
      "sr_t_at": "null",
      "sr_object_type": "p",
      "sr_t_td": "null",
      "sr_scene": "2",
      "sr_match_score": "0.6861",
      "sr_pvid": "0c2824d7#9ffe#4dc2#bcdf#0d92c6f7f54c",
      "mtx_bucket": "null",
      "sr_object_id": "5654537",
      "sr_ctt_goods": "null",
      "sr_pageno": "1",
      "sr_trigger_w": "null",
      "sr_cate": "736",
      "sr_ctr": "null",
      "sr_tc_ctr": "null",
      "sr_final_score": "null",
      "sr_tc_clk": "null",
      "sr_tc_td": "null",
      "sr_pinleici": "唇膏"
      }
      },
      "currentPrice": 139.00,
      "vip" :128,
      "similarLinkUrl": "http://m.kaola.com/klapp?klpn=similarGoodsPage&goods_id=5654537",
      "showFeed": false
      },
      {
      "recType": 22,
      "countryLogo": "http://kaola-haitao.oss.kaolacdn.com/1077833fa2854dcb97502084f24f449d1419659976324i46kw8bh10001.png",
      "linkUrl": "https://m-goods.kaola.com/product/6103884.html",
      "goodsImage": "http://kaola-haitao.oss.kaolacdn.com/c4f0c185f2cb4ab5ab1776e49619d702_800_800.jpg",
      "goodsImage1":"https://kaola-pop.oss.kaolacdn.com/1b91563530744a998a6fd86a0fa5430c_800_800.jpg?x-oss-process=image/resize,w_262,h_262/quality,q_90",
      "scm": "v1.1008.1008_p_6103884.234618_234266_91519.cate_736-cts_1599708057070-channel_2-fccrowds_ul-pinleici_-match&udl;score_0&doot;6317-bucketid_null-abid_183397-trigger&udl;weight_null-content&udl;type_1-pvid_0c2824d7#9ffe#4dc2#bcdf#0d92c6f7f54c-price_62&doot;0-pageno_1-appid_18806-match&udl;type_21-position_6-brand_4291-expid_null",
      "goodsName": "【保税仓闪电发货】【新款尤",
      "goodMinName":"雾弹 泫雅色】MAC 魅可 子弹头口红唇膏 3g/1.8g",
      "realTimeRec": false,
      "titleForeHeadLabelList": [

      ],
      "contrastPriceInfo": {
      "contrastPrice": "58",
      "priceType": 4
      },
      "labelListWithStyle": [
      {
      "styleCode": 202,
      "content": "满2件减10"
      },
      {
      "styleCode": 202,
      "content": "特价"
      }
      ],
      "enjoyPriceInfo": {
      "enjoyPrice": "62",
      "priceType": 0
      },
      "countryName": "魅可",
      "template": {
      "name": "kl_feed_goods",
      "version": "7",
      "url": "https://ossgw.alicdn.com/rapid-oss-bucket/1599199439687/kl_feed_goods.zip"
      },
      "goodsId": 6103884,
      "categoryName": "唇膏/口红",
      "imageUrl": "http://kaola-pop.oss.kaolacdn.com/efe6d2c3dd46407c96b5e589f217deb6_800_800.jpg",
      "trackInfo": {
      "utScm": "20140737.p_6103884.234618_234266_91519.cate_736-cts_1599708057070-channel_2-fccrowds_ul-bucketid_null-contenttype_1-matchscore_6317-pvid_0c2824d7#9ffe#4dc2#bcdf#0d92c6f7f54c-price_620000-pageno_1-appid_18806-matchtype_21-triggerweight_null-position_6-brand_4291-expid_null",
      "utLogMap": {
      "sr_price": "62.0",
      "sr_abid": "183397",
      "sr_trigger": "null",
      "sr_brand": "4291",
      "sr_pos": "6",
      "sr_appid": "18806",
      "sr_rank_score": "null",
      "mtx_exp": "null",
      "sr_cvr": "null",
      "sr_ctt_type": "null",
      "sr_match_type": "21",
      "sr_recall_score": "null",
      "mtx_crowds": "null",
      "sr_t_at": "null",
      "sr_object_type": "p",
      "sr_t_td": "null",
      "sr_scene": "2",
      "sr_match_score": "0.6317",
      "sr_pvid": "0c2824d7#9ffe#4dc2#bcdf#0d92c6f7f54c",
      "mtx_bucket": "null",
      "sr_object_id": "6103884",
      "sr_ctt_goods": "null",
      "sr_pageno": "1",
      "sr_trigger_w": "null",
      "sr_cate": "736",
      "sr_ctr": "null",
      "sr_tc_ctr": "null",
      "sr_final_score": "null",
      "sr_tc_clk": "null",
      "sr_tc_td": "null",
      "sr_pinleici": ""
      }
      },
      "currentPrice": 62.00,
      "vip" :58,
      "similarLinkUrl": "http://m.kaola.com/klapp?klpn=similarGoodsPage&goods_id=6103884",
      "showFeed": false
      },
      {
      "recType": 22,
      "countryLogo": "http://kaola-haitao.oss.kaolacdn.com/c0be3e6c11de4adb9ea90df712da9aea1419662386933i46mbwfo10003.png",
      "linkUrl": "https://m-goods.kaola.com/product/1383664.html",
      "goodsImage": "http://kaola-haitao.oss.kaolacdn.com/849868fd7796453ca8e6c29691361657_800_800.jpg",
      "goodsImage1":"https://kaola-haitao.oss.kaolacdn.com/634f80653e6f47aeb07eb83435128dfb_800_800.jpg?x-oss-process=image/resize,w_262,h_262/quality,q_90",
      "scm": "v1.1008.1008_p_1383664.234618_234266_91519.cate_106177-cts_1599708057070-channel_2-fccrowds_ul-pinleici_面膜-match&udl;score_0&doot;6297-bucketid_null-abid_183397-trigger&udl;weight_null-content&udl;type_1-pvid_0c2824d7#9ffe#4dc2#bcdf#0d92c6f7f54c-price_138&doot;0-pageno_1-appid_18806-match&udl;type_21-position_7-brand_2899-expid_null",
      "goodsName": "【3盒装 】Dr.Jart+ 蒂佳婷宛",
      "goodMinName":"若新生水漾保湿急救面膜",
      "realTimeRec": false,
      "titleForeHeadLabelList": [
      "https://kaola-haitao.oss.kaolacdn.com/e37aaf47-b4e4-4602-8309-5edf8a2300f8T2008031346_78_39.png?klsize=78x39"
      ],
      "contrastPriceInfo": {
      "contrastPrice": "132",
      "priceType": 4
      },
      "labelListWithStyle": [
      {
      "styleCode": 202,
      "content": "豆抵1元"
      },
      {
      "styleCode": 202,
      "content": "特价"
      }
      ],
      "enjoyPriceInfo": {
      "enjoyPrice": "138",
      "priceType": 0
      },
      "countryName": "Dr.Jart+",
      "template": {
      "name": "kl_feed_goods",
      "version": "7",
      "url": "https://ossgw.alicdn.com/rapid-oss-bucket/1599199439687/kl_feed_goods.zip"
      },
      "goodsId": 1383664,
      "categoryName": "贴片面膜",
      "imageUrl": "http://kaola-haitao.oss.kaolacdn.com/f6301175f47e492ab18a7962a99d32761565262946012jz2l56ti11741.jpg",
      "trackInfo": {
      "utScm": "20140737.p_1383664.234618_234266_91519.cate_106177-cts_1599708057070-channel_2-fccrowds_ul-bucketid_null-contenttype_1-matchscore_6297-pvid_0c2824d7#9ffe#4dc2#bcdf#0d92c6f7f54c-price_1380000-pageno_1-appid_18806-matchtype_21-triggerweight_null-position_7-brand_2899-expid_null",
      "utLogMap": {
      "sr_price": "138.0",
      "sr_abid": "183397",
      "sr_trigger": "null",
      "sr_brand": "2899",
      "sr_pos": "7",
      "sr_appid": "18806",
      "sr_rank_score": "null",
      "mtx_exp": "null",
      "sr_cvr": "null",
      "sr_ctt_type": "null",
      "sr_match_type": "21",
      "sr_recall_score": "null",
      "mtx_crowds": "null",
      "sr_t_at": "null",
      "sr_object_type": "p",
      "sr_t_td": "null",
      "sr_scene": "2",
      "sr_match_score": "0.6297",
      "sr_pvid": "0c2824d7#9ffe#4dc2#bcdf#0d92c6f7f54c",
      "mtx_bucket": "null",
      "sr_object_id": "1383664",
      "sr_ctt_goods": "null",
      "sr_pageno": "1",
      "sr_trigger_w": "null",
      "sr_cate": "106177",
      "sr_ctr": "null",
      "sr_tc_ctr": "null",
      "sr_final_score": "null",
      "sr_tc_clk": "null",
      "sr_tc_td": "null",
      "sr_pinleici": "面膜"
      }
      },
      "currentPrice": 138.00,
      "vip" :94,
      "similarLinkUrl": "http://m.kaola.com/klapp?klpn=similarGoodsPage&goods_id=1383664",
      "showFeed": false
      },
      {
      "recType": 22,
      "countryLogo": "http://kaola-haitao.oss.kaolacdn.com/1077833fa2854dcb97502084f24f449d1419659976324i46kw8bh10001.png",
      "linkUrl": "https://m-goods.kaola.com/product/1498526.html",
      "goodsImage": "http://kaola-haitao.oss.kaolacdn.com/1f7bb24b733e4bd9b9cecde92654d815_800_800.jpg",
      "goodsImage1":"https://kaola-pop.oss.kaolacdn.com/31bc159ecf6443d29f2eb15cf0cc9db4_800_800.jpg?x-oss-process=image/resize,w_262,h_262/quality,q_90",
      "scm": "v1.1008.1008_p_1498526.234618_234266_91519.cate_112044-cts_1599708057070-channel_2-fccrowds_ul-pinleici_菌菇水-match&udl;score_0&doot;593-bucketid_null-abid_183397-trigger&udl;weight_null-content&udl;type_1-pvid_0c2824d7#9ffe#4dc2#bcdf#0d92c6f7f54c-price_169&doot;0-pageno_1-appid_18806-match&udl;type_21-position_8-brand_2345-expid_null",
      "goodsName": "【王一博同款】ORIGINS 悦",
      "goodMinName":"木之源 灵芝焕能精华水 菌菇水 200毫升",
      "realTimeRec": false,
      "titleForeHeadLabelList": [
      "https://kaola-haitao.oss.kaolacdn.com/e37aaf47-b4e4-4602-8309-5edf8a2300f8T2008031346_78_39.png?klsize=78x39"
      ],
      "contrastPriceInfo": {
      "contrastPrice": "149",
      "priceType": 4
      },
      "labelListWithStyle": [
      {
      "styleCode": 202,
      "content": "豆抵2元"
      },
      {
      "styleCode": 202,
      "content": "特价"
      }
      ],
      "enjoyPriceInfo": {
      "enjoyPrice": "169",
      "priceType": 0
      },
      "countryName": "悦木之源",
      "template": {
      "name": "kl_feed_goods",
      "version": "7",
      "url": "https://ossgw.alicdn.com/rapid-oss-bucket/1599199439687/kl_feed_goods.zip"
      },
      "goodsId": 1498526,
      "categoryName": "化妆水/爽肤水",
      "imageUrl": "http://kaola-haitao.oss.kaolacdn.com/1877c80fc8464c7496ca9770ef4dfc271584691661779F92E1015301F446F28A1DD5E42A0F419.jpg",
      "trackInfo": {
      "utScm": "20140737.p_1498526.234618_234266_91519.cate_112044-cts_1599708057070-channel_2-fccrowds_ul-bucketid_null-contenttype_1-matchscore_5930-pvid_0c2824d7#9ffe#4dc2#bcdf#0d92c6f7f54c-price_1690000-pageno_1-appid_18806-matchtype_21-triggerweight_null-position_8-brand_2345-expid_null",
      "utLogMap": {
      "sr_price": "169.0",
      "sr_abid": "183397",
      "sr_trigger": "null",
      "sr_brand": "2345",
      "sr_pos": "8",
      "sr_appid": "18806",
      "sr_rank_score": "null",
      "mtx_exp": "null",
      "sr_cvr": "null",
      "sr_ctt_type": "null",
      "sr_match_type": "21",
      "sr_recall_score": "null",
      "mtx_crowds": "null",
      "sr_t_at": "null",
      "sr_object_type": "p",
      "sr_t_td": "null",
      "sr_scene": "2",
      "sr_match_score": "0.593",
      "sr_pvid": "0c2824d7#9ffe#4dc2#bcdf#0d92c6f7f54c",
      "mtx_bucket": "null",
      "sr_object_id": "1498526",
      "sr_ctt_goods": "null",
      "sr_pageno": "1",
      "sr_trigger_w": "null",
      "sr_cate": "112044",
      "sr_ctr": "null",
      "sr_tc_ctr": "null",
      "sr_final_score": "null",
      "sr_tc_clk": "null",
      "sr_tc_td": "null",
      "sr_pinleici": "菌菇水"
      }
      },
      "currentPrice": 169.00,
      "vip" :148,
      "similarLinkUrl": "http://m.kaola.com/klapp?klpn=similarGoodsPage&goods_id=1498526",
      "showFeed": false
      },
      {
      "recType": 22,
      "countryLogo": "http://kaola-haitao.oss.kaolacdn.com/1077833fa2854dcb97502084f24f449d1419659976324i46kw8bh10001.png",
      "linkUrl": "https://m-goods.kaola.com/product/279504.html",
      "goodsImage": "http://kaola-haitao.oss.kaolacdn.com/233374dffe4743b6992cfa02e4ac2959_800_800.jpg",
      "goodsImage1":"https://kaola-pop.oss.kaolacdn.com/b16a5e6780f4420c95cd874df32d5642_800_800.jpg?x-oss-process=image/resize,w_262,h_262/quality,q_90",
      "scm": "v1.1008.1008_p_279504.234618_234266_91519.cate_112047-cts_1599708057070-channel_2-fccrowds_ul-pinleici_面膜-match&udl;score_0&doot;5848-bucketid_null-abid_183397-trigger&udl;weight_null-content&udl;type_1-pvid_0c2824d7#9ffe#4dc2#bcdf#0d92c6f7f54c-price_249&doot;0-pageno_1-appid_18806-match&udl;type_21-position_9-brand_1447-expid_null",
      "goodsName": "【阚清子同款】Kiehl's 科颜",
      "goodMinName":"氏 亚马逊白泥面膜125毫升 专柜当家明星",
      "realTimeRec": false,
      "titleForeHeadLabelList": [
      "https://kaola-haitao.oss.kaolacdn.com/e37aaf47-b4e4-4602-8309-5edf8a2300f8T2008031346_78_39.png?klsize=78x39"
      ],
      "contrastPriceInfo": {
      "contrastPrice": "209",
      "priceType": 4
      },
      "labelListWithStyle": [
      {
      "styleCode": 202,
      "content": "豆抵1元"
      },
      {
      "styleCode": 202,
      "content": "特卖"
      }
      ],
      "enjoyPriceInfo": {
      "enjoyPrice": "249",
      "priceType": 0
      },
      "countryName": "科颜氏",
      "template": {
      "name": "kl_feed_goods",
      "version": "7",
      "url": "https://ossgw.alicdn.com/rapid-oss-bucket/1599199439687/kl_feed_goods.zip"
      },
      "goodsId": 279504,
      "categoryName": "涂抹面膜",
      "imageUrl": "http://kaola-haitao.oss.kaolacdn.com/3e66cc82de6b497aaefdb7f6936d675a1563507202923jy9jtilo10264.jpg",
      "trackInfo": {
      "utScm": "20140737.p_279504.234618_234266_91519.cate_112047-cts_1599708057070-channel_2-fccrowds_ul-bucketid_null-contenttype_1-matchscore_5848-pvid_0c2824d7#9ffe#4dc2#bcdf#0d92c6f7f54c-price_2490000-pageno_1-appid_18806-matchtype_21-triggerweight_null-position_9-brand_1447-expid_null",
      "utLogMap": {
      "sr_price": "249.0",
      "sr_abid": "183397",
      "sr_trigger": "null",
      "sr_brand": "1447",
      "sr_pos": "9",
      "sr_appid": "18806",
      "sr_rank_score": "null",
      "mtx_exp": "null",
      "sr_cvr": "null",
      "sr_ctt_type": "null",
      "sr_match_type": "21",
      "sr_recall_score": "null",
      "mtx_crowds": "null",
      "sr_t_at": "null",
      "sr_object_type": "p",
      "sr_t_td": "null",
      "sr_scene": "2",
      "sr_match_score": "0.5848",
      "sr_pvid": "0c2824d7#9ffe#4dc2#bcdf#0d92c6f7f54c",
      "mtx_bucket": "null",
      "sr_object_id": "279504",
      "sr_ctt_goods": "null",
      "sr_pageno": "1",
      "sr_trigger_w": "null",
      "sr_cate": "112047",
      "sr_ctr": "null",
      "sr_tc_ctr": "null",
      "sr_final_score": "null",
      "sr_tc_clk": "null",
      "sr_tc_td": "null",
      "sr_pinleici": "面膜"
      }
      },
      "currentPrice": 249.00,
      "vip" :239,
      "similarLinkUrl": "http://m.kaola.com/klapp?klpn=similarGoodsPage&goods_id=279504",
      "showFeed": false
      },
      {
      "recType": 22,
      "countryLogo": "http://kaola-haitao.oss.kaolacdn.com/1077833fa2854dcb97502084f24f449d1419659976324i46kw8bh10001.png",
      "linkUrl": "https://m-goods.kaola.com/product/2490312.html",
      "goodsImage": "http://kaola-haitao.oss.kaolacdn.com/70d534fb12444c1e90ed731614ccad60_800_800.jpg",
      "goodsImage1":"https://kaola-pop.oss.kaolacdn.com/b65f70515c3149d18533d5c39f047eeb_800_800.jpg?x-oss-process=image/resize,w_262,h_262/quality,q_90",
      "scm": "v1.1008.1008_p_2490312.234618_234266_91519.cate_567-cts_1599708057070-channel_2-fccrowds_ul-pinleici_眼霜-match&udl;score_0&doot;5374-bucketid_null-abid_183397-trigger&udl;weight_null-content&udl;type_1-pvid_0c2824d7#9ffe#4dc2#bcdf#0d92c6f7f54c-price_388&doot;0-pageno_1-appid_18806-match&udl;type_21-position_10-brand_1566-expid_null",
      "goodsName": "ESTĒE LAUDER 雅诗兰黛 ",
      "goodMinName":"特润修护精华眼霜 小棕瓶“抗蓝光”眼霜 15毫升",
      "realTimeRec": false,
      "titleForeHeadLabelList": [
      "https://kaola-haitao.oss.kaolacdn.com/e37aaf47-b4e4-4602-8309-5edf8a2300f8T2008031346_78_39.png?klsize=78x39"
      ],
      "contrastPriceInfo": {
      "contrastPrice": "348",
      "priceType": 4
      },
      "labelListWithStyle": [
      {
      "styleCode": 202,
      "content": "特价"
      },
      {
      "styleCode": 300,
      "content": "包税"
      }
      ],
      "enjoyPriceInfo": {
      "enjoyPrice": "388",
      "priceType": 0
      },
      "countryName": "雅诗兰黛",
      "template": {
      "name": "kl_feed_goods",
      "version": "7",
      "url": "https://ossgw.alicdn.com/rapid-oss-bucket/1599199439687/kl_feed_goods.zip"
      },
      "goodsId": 2490312,
      "categoryName": "眼霜",
      "imageUrl": "http://kaola-haitao.oss.kaolacdn.com/ee8462b2ef1742cd96ad38e1343c43df1561970261376jxk4rj3g10319.jpg",
      "trackInfo": {
      "utScm": "20140737.p_2490312.234618_234266_91519.cate_567-cts_1599708057070-channel_2-fccrowds_ul-bucketid_null-contenttype_1-matchscore_5374-pvid_0c2824d7#9ffe#4dc2#bcdf#0d92c6f7f54c-price_3880000-pageno_1-appid_18806-matchtype_21-triggerweight_null-position_10-brand_1566-expid_null",
      "utLogMap": {
      "sr_price": "388.0",
      "sr_abid": "183397",
      "sr_trigger": "null",
      "sr_brand": "1566",
      "sr_pos": "10",
      "sr_appid": "18806",
      "sr_rank_score": "null",
      "mtx_exp": "null",
      "sr_cvr": "null",
      "sr_ctt_type": "null",
      "sr_match_type": "21",
      "sr_recall_score": "null",
      "mtx_crowds": "null",
      "sr_t_at": "null",
      "sr_object_type": "p",
      "sr_t_td": "null",
      "sr_scene": "2",
      "sr_match_score": "0.5374",
      "sr_pvid": "0c2824d7#9ffe#4dc2#bcdf#0d92c6f7f54c",
      "mtx_bucket": "null",
      "sr_object_id": "2490312",
      "sr_ctt_goods": "null",
      "sr_pageno": "1",
      "sr_trigger_w": "null",
      "sr_cate": "567",
      "sr_ctr": "null",
      "sr_tc_ctr": "null",
      "sr_final_score": "null",
      "sr_tc_clk": "null",
      "sr_tc_td": "null",
      "sr_pinleici": "眼霜"
      }
      },
      "currentPrice": 388.00,
      "vip" :368,

      "similarLinkUrl": "http://m.kaola.com/klapp?klpn=similarGoodsPage&goods_id=2490312",
      "showFeed": false
      },
      {
      "recType": 22,
      "countryLogo": "http://kaola-haitao.oss.kaolacdn.com/d3c18d60f0e54c32af5cf24d18be585b1419662519909i46mer1g10007.png",
      "linkUrl": "https://m-goods.kaola.com/product/2893859.html",
      "goodsImage1":"https://kaola-pop.oss.kaolacdn.com/1fd6b97a550248248e9448c6913ca95c_800_800.jpg?x-oss-process=image/resize,w_262,h_262/quality,q_90",
      "goodsImage": "http://kaola-haitao.oss.kaolacdn.com/5ffe3cee6b474e618654b7fdb0728f271586400873168B89FAFA0877A986E38059807EA640F13.jpg",
      "scm": "v1.1008.1008_p_2893859.234618_234266_91519.cate_736-cts_1599708057070-channel_2-fccrowds_ul-pinleici_唇膏-match&udl;score_0&doot;529-bucketid_null-abid_183397-trigger&udl;weight_null-content&udl;type_1-pvid_0c2824d7#9ffe#4dc2#bcdf#0d92c6f7f54c-price_269&doot;0-pageno_1-appid_18806-match&udl;type_21-position_11-brand_1568-expid_null",
      "goodsName": "【新款番茄红333 N37】",
      "goodMinName":"GIVENCHY 纪梵希 高定香榭小羊皮唇膏 3.4克",
      "realTimeRec": false,
      "titleForeHeadLabelList": [
      "https://kaola-haitao.oss.kaolacdn.com/e37aaf47-b4e4-4602-8309-5edf8a2300f8T2008031346_78_39.png?klsize=78x39"
      ],
      "contrastPriceInfo": {
      "contrastPrice": "247",
      "priceType": 4
      },
      "labelListWithStyle": [
      {
      "styleCode": 202,
      "content": "豆抵0.5元"
      },
      {
      "styleCode": 300,
      "content": "包税"
      }
      ],
      "enjoyPriceInfo": {
      "enjoyPrice": "269",
      "priceType": 0
      },
      "countryName": "纪梵希",
      "template": {
      "name": "kl_feed_goods",
      "version": "7",
      "url": "https://ossgw.alicdn.com/rapid-oss-bucket/1599199439687/kl_feed_goods.zip"
      },
      "goodsId": 2893859,
      "categoryName": "唇膏/口红",
      "imageUrl": "http://kaola-haitao.oss.kaolacdn.com/5ffe3cee6b474e618654b7fdb0728f271586400873168B89FAFA0877A986E38059807EA640F13.jpg",
      "trackInfo": {
      "utScm": "20140737.p_2893859.234618_234266_91519.cate_736-cts_1599708057070-channel_2-fccrowds_ul-bucketid_null-contenttype_1-matchscore_5290-pvid_0c2824d7#9ffe#4dc2#bcdf#0d92c6f7f54c-price_2690000-pageno_1-appid_18806-matchtype_21-triggerweight_null-position_11-brand_1568-expid_null",
      "utLogMap": {
      "sr_price": "269.0",
      "sr_abid": "183397",
      "sr_trigger": "null",
      "sr_brand": "1568",
      "sr_pos": "11",
      "sr_appid": "18806",
      "sr_rank_score": "null",
      "mtx_exp": "null",
      "sr_cvr": "null",
      "sr_ctt_type": "null",
      "sr_match_type": "21",
      "sr_recall_score": "null",
      "mtx_crowds": "null",
      "sr_t_at": "null",
      "sr_object_type": "p",
      "sr_t_td": "null",
      "sr_scene": "2",
      "sr_match_score": "0.529",
      "sr_pvid": "0c2824d7#9ffe#4dc2#bcdf#0d92c6f7f54c",
      "mtx_bucket": "null",
      "sr_object_id": "2893859",
      "sr_ctt_goods": "null",
      "sr_pageno": "1",
      "sr_trigger_w": "null",
      "sr_cate": "736",
      "sr_ctr": "null",
      "sr_tc_ctr": "null",
      "sr_final_score": "null",
      "sr_tc_clk": "null",
      "sr_tc_td": "null",
      "sr_pinleici": "唇膏"
      }
      },
      "currentPrice": 269,
      "vip" :239,
      "similarLinkUrl": "http://m.kaola.com/klapp?klpn=similarGoodsPage&goods_id=2893859",
      "showFeed": false
      },
      {
      "recType": 22,
      "countryLogo": "http://kaola-haitao.oss.kaolacdn.com/1077833fa2854dcb97502084f24f449d1419659976324i46kw8bh10001.png",
      "linkUrl": "https://m-goods.kaola.com/product/2892076.html",
      "goodsImage": "http://kaola-haitao.oss.kaolacdn.com/885bb661fbae4efd9619a8c564643fdd_800_800.jpg",
      "goodsImage1":"https://kaola-pop.oss.kaolacdn.com/01964a49564049f6ab2a7eeb63412334_800_800.jpg?x-oss-process=image/resize,w_262,h_262/quality,q_90",
      "scm": "v1.1008.1008_p_2892076.234618_234266_91519.cate_728-cts_1599708057070-channel_2-fccrowds_ul-pinleici_粉底液-match&udl;score_0&doot;5104-bucketid_null-abid_183397-trigger&udl;weight_null-content&udl;type_1-pvid_0c2824d7#9ffe#4dc2#bcdf#0d92c6f7f54c-price_268&doot;0-pageno_1-appid_18806-match&udl;type_21-position_12-brand_1566-expid_null",
      "goodsName": "ESTĒE LAUDER 雅诗兰黛 ",
      "goodMinName":"持妆粉底液 30毫升  无泵头款",
      "realTimeRec": false,
      "titleForeHeadLabelList": [
      "https://kaola-haitao.oss.kaolacdn.com/e37aaf47-b4e4-4602-8309-5edf8a2300f8T2008031346_78_39.png?klsize=78x39"
      ],
      "contrastPriceInfo": {
      "contrastPrice": "248",
      "priceType": 4
      },
      "labelListWithStyle": [
      {
      "styleCode": 202,
      "content": "豆抵2.6元"
      },
      {
      "styleCode": 202,
      "content": "特价"
      }
      ],
      "enjoyPriceInfo": {
      "enjoyPrice": "268",
      "priceType": 0
      },
      "countryName": "雅诗兰黛",
      "template": {
      "name": "kl_feed_goods",
      "version": "7",
      "url": "https://ossgw.alicdn.com/rapid-oss-bucket/1599199439687/kl_feed_goods.zip"
      },
      "goodsId": 2892076,
      "categoryName": "粉底液/膏",
      "imageUrl": "http://kaola-haitao.oss.kaolacdn.com/04c252b4ac9c4a7d93181a1f9024d6951573092402964k2o2lmgt11428.jpg",
      "trackInfo": {
      "utScm": "20140737.p_2892076.234618_234266_91519.cate_728-cts_1599708057070-channel_2-fccrowds_ul-bucketid_null-contenttype_1-matchscore_5104-pvid_0c2824d7#9ffe#4dc2#bcdf#0d92c6f7f54c-price_2680000-pageno_1-appid_18806-matchtype_21-triggerweight_null-position_12-brand_1566-expid_null",
      "utLogMap": {
      "sr_price": "268.0",
      "sr_abid": "183397",
      "sr_trigger": "null",
      "sr_brand": "1566",
      "sr_pos": "12",
      "sr_appid": "18806",
      "sr_rank_score": "null",
      "mtx_exp": "null",
      "sr_cvr": "null",
      "sr_ctt_type": "null",
      "sr_match_type": "21",
      "sr_recall_score": "null",
      "mtx_crowds": "null",
      "sr_t_at": "null",
      "sr_object_type": "p",
      "sr_t_td": "null",
      "sr_scene": "2",
      "sr_match_score": "0.5104",
      "sr_pvid": "0c2824d7#9ffe#4dc2#bcdf#0d92c6f7f54c",
      "mtx_bucket": "null",
      "sr_object_id": "2892076",
      "sr_ctt_goods": "null",
      "sr_pageno": "1",
      "sr_trigger_w": "null",
      "sr_cate": "728",
      "sr_ctr": "null",
      "sr_tc_ctr": "null",
      "sr_final_score": "null",
      "sr_tc_clk": "null",
      "sr_tc_td": "null",
      "sr_pinleici": "粉底液"
      }
      },
      "currentPrice": 268.00,
      "vip" :258,
      "similarLinkUrl": "http://m.kaola.com/klapp?klpn=similarGoodsPage&goods_id=2892076",
      "showFeed": false
      },
      {
      "recType": 22,
      "countryLogo": "http://kaola-haitao.oss.kaolacdn.com/9ab013a727024145ae377c9a1b6286551419662432571i46mcvne10004.png",
      "linkUrl": "https://m-goods.kaola.com/product/2892071.html",
      "goodsImage1":"https://kaola-haitao.oss.kaolacdn.com/1e7n0rd2f89_800_800.jpg?x-oss-process=image/resize,w_262,h_262/quality,q_90",
      "goodsImage": "http://kaola-haitao.oss.kaolacdn.com/c24095247afe4eccbdab318fd4e208d4_800_800.jpg",
      "scm": "v1.1008.1008_p_2892071.234618_234266_91519.cate_737-cts_1599708057070-channel_2-fccrowds_ul-pinleici_唇釉-match&udl;score_0&doot;473-bucketid_null-abid_183397-trigger&udl;weight_null-content&udl;type_1-pvid_0c2824d7#9ffe#4dc2#bcdf#0d92c6f7f54c-price_199&doot;0-pageno_1-appid_18806-match&udl;type_21-position_13-brand_1453-expid_null",
      "goodsName": "【易烊千玺代言】【热门",
      "goodMinName":"#206 #415#405】阿玛尼臻致丝绒哑光红管唇釉 显白枫叶红 山楂红415",
      "realTimeRec": false,
      "titleForeHeadLabelList": [
      "https://kaola-haitao.oss.kaolacdn.com/e37aaf47-b4e4-4602-8309-5edf8a2300f8T2008031346_78_39.png?klsize=78x39"
      ],
      "contrastPriceInfo": {
      "contrastPrice": "189",
      "priceType": 4
      },
      "labelListWithStyle": [
      {
      "styleCode": 202,
      "content": "豆抵0.5元"
      },
      {
      "styleCode": 202,
      "content": "特价"
      }
      ],
      "enjoyPriceInfo": {
      "enjoyPrice": "199",
      "priceType": 0
      },
      "countryName": "乔治·阿玛尼",
      "template": {
      "name": "kl_feed_goods",
      "version": "7",
      "url": "https://ossgw.alicdn.com/rapid-oss-bucket/1599199439687/kl_feed_goods.zip"
      },
      "goodsId": 2892071,
      "categoryName": "唇彩/唇蜜/唇釉",
      "imageUrl": "http://kaola-haitao.oss.kaolacdn.com/3598a7028fd74c8989d9254229fa56ce1574994300640k3jixw3z10614.jpg",
      "trackInfo": {
      "utScm": "20140737.p_2892071.234618_234266_91519.cate_737-cts_1599708057070-channel_2-fccrowds_ul-bucketid_null-contenttype_1-matchscore_4730-pvid_0c2824d7#9ffe#4dc2#bcdf#0d92c6f7f54c-price_1990000-pageno_1-appid_18806-matchtype_21-triggerweight_null-position_13-brand_1453-expid_null",
      "utLogMap": {
      "sr_price": "199.0",
      "sr_abid": "183397",
      "sr_trigger": "null",
      "sr_brand": "1453",
      "sr_pos": "13",
      "sr_appid": "18806",
      "sr_rank_score": "null",
      "mtx_exp": "null",
      "sr_cvr": "null",
      "sr_ctt_type": "null",
      "sr_match_type": "21",
      "sr_recall_score": "null",
      "mtx_crowds": "null",
      "sr_t_at": "null",
      "sr_object_type": "p",
      "sr_t_td": "null",
      "sr_scene": "2",
      "sr_match_score": "0.473",
      "sr_pvid": "0c2824d7#9ffe#4dc2#bcdf#0d92c6f7f54c",
      "mtx_bucket": "null",
      "sr_object_id": "2892071",
      "sr_ctt_goods": "null",
      "sr_pageno": "1",
      "sr_trigger_w": "null",
      "sr_cate": "737",
      "sr_ctr": "null",
      "sr_tc_ctr": "null",
      "sr_final_score": "null",
      "sr_tc_clk": "null",
      "sr_tc_td": "null",
      "sr_pinleici": "唇釉"
      }
      },
      "currentPrice": 199.00,
      "vip" :188,
      "similarLinkUrl": "http://m.kaola.com/klapp?klpn=similarGoodsPage&goods_id=2892071",
      "showFeed": false
      },
      {
      "recType": 22,
      "countryLogo": "http://kaola-haitao.oss.kaolacdn.com/1cc2m9est21_46_46.png",
      "linkUrl": "https://m-goods.kaola.com/product/2085086.html",
      "goodsImage1":"https://kaola-haitao.oss.kaolacdn.com/5d057671c57542b0b502e27d70b78dfd15900459325765702A110065CB5711E68386011E467E0.jpg?x-oss-process=image/resize,w_262,h_262/quality,q_90",
      "goodsImage": "http://kaola-haitao.oss.kaolacdn.com/75f004fe514f4e53ad740e0778c125eb_800_800.jpg",
      "scm": "v1.1008.1008_p_2085086.234618_234266_91519.cate_114039-cts_1599708057070-channel_2-fccrowds_ul-pinleici_防晒露-match&udl;score_0&doot;4668-bucketid_null-abid_183397-trigger&udl;weight_null-content&udl;type_1-pvid_0c2824d7#9ffe#4dc2#bcdf#0d92c6f7f54c-price_189&doot;0-pageno_1-appid_18806-match&udl;type_21-position_14-brand_1200-expid_null",
      "goodsName": "SHISEIDO 资生堂安热沙小",
      "goodMinName":"金瓶防晒露SPF50+PA++++  60毫升 新老版本随机发货",
      "realTimeRec": false,
      "titleForeHeadLabelList": [
      "https://kaola-haitao.oss.kaolacdn.com/e37aaf47-b4e4-4602-8309-5edf8a2300f8T2008031346_78_39.png?klsize=78x39"
      ],
      "contrastPriceInfo": {
      "contrastPrice": "155",
      "priceType": 4
      },
      "labelListWithStyle": [
      {
      "styleCode": 202,
      "content": "豆抵2元"
      },
      {
      "styleCode": 202,
      "content": "特价"
      }
      ],
      "enjoyPriceInfo": {
      "enjoyPrice": "189",
      "priceType": 0
      },
      "countryName": "资生堂",
      "template": {
      "name": "kl_feed_goods",
      "version": "7",
      "url": "https://ossgw.alicdn.com/rapid-oss-bucket/1599199439687/kl_feed_goods.zip"
      },
      "goodsId": 2085086,
      "categoryName": "防晒霜",
      "imageUrl": "http://kaola-haitao.oss.kaolacdn.com/729b3d61f0314c34bc25b7bf9823f00915900474227445D9DB2BFD8E43969D43965FC712E33E6.jpg",
      "trackInfo": {
      "utScm": "20140737.p_2085086.234618_234266_91519.cate_114039-cts_1599708057071-channel_2-fccrowds_ul-bucketid_null-contenttype_1-matchscore_4668-pvid_0c2824d7#9ffe#4dc2#bcdf#0d92c6f7f54c-price_1890000-pageno_1-appid_18806-matchtype_21-triggerweight_null-position_14-brand_1200-expid_null",
      "utLogMap": {
      "sr_price": "189.0",
      "sr_abid": "183397",
      "sr_trigger": "null",
      "sr_brand": "1200",
      "sr_pos": "14",
      "sr_appid": "18806",
      "sr_rank_score": "null",
      "mtx_exp": "null",
      "sr_cvr": "null",
      "sr_ctt_type": "null",
      "sr_match_type": "21",
      "sr_recall_score": "null",
      "mtx_crowds": "null",
      "sr_t_at": "null",
      "sr_object_type": "p",
      "sr_t_td": "null",
      "sr_scene": "2",
      "sr_match_score": "0.4668",
      "sr_pvid": "0c2824d7#9ffe#4dc2#bcdf#0d92c6f7f54c",
      "mtx_bucket": "null",
      "sr_object_id": "2085086",
      "sr_ctt_goods": "null",
      "sr_pageno": "1",
      "sr_trigger_w": "null",
      "sr_cate": "114039",
      "sr_ctr": "null",
      "sr_tc_ctr": "null",
      "sr_final_score": "null",
      "sr_tc_clk": "null",
      "sr_tc_td": "null",
      "sr_pinleici": "防晒露"
      }
      },
      "currentPrice": 189.00,
      "vip" :178,
      "similarLinkUrl": "http://m.kaola.com/klapp?klpn=similarGoodsPage&goods_id=2085086",
      "showFeed": false
      },
      {
      "recType": 22,
      "countryLogo": "http://kaola-haitao.oss.kaolacdn.com/d3c18d60f0e54c32af5cf24d18be585b1419662519909i46mer1g10007.png",
      "linkUrl": "https://m-goods.kaola.com/product/279619.html",
      "goodsImage1":"https://kaola-haitao.oss.kaolacdn.com/3d2f0afa0f64454fae4fc7a3c49d29c01556091032565juuwf93u10532.jpg?x-oss-process=image/resize,w_262,h_262/quality,q_90",
      "goodsImage": "http://kaola-haitao.oss.kaolacdn.com/05a74754645844fd808db831a1150d68_800_800.jpg",
      "scm": "v1.1008.1008_p_279619.234618_234266_91519.cate_112044-cts_1599708057071-channel_2-fccrowds_ul-pinleici_爽肤水-match&udl;score_0&doot;4534-bucketid_null-abid_183397-trigger&udl;weight_null-content&udl;type_1-pvid_0c2824d7#9ffe#4dc2#bcdf#0d92c6f7f54c-price_289&doot;0-pageno_1-appid_18806-match&udl;type_21-position_15-brand_1452-expid_null",
      "goodsName": "LANCÔME 兰蔻 玫瑰露清滢",
      "goodMinName":"柔肤粉水 400毫升 干皮真爱",
      "realTimeRec": false,
      "titleForeHeadLabelList": [
      "https://kaola-haitao.oss.kaolacdn.com/e37aaf47-b4e4-4602-8309-5edf8a2300f8T2008031346_78_39.png?klsize=78x39"
      ],
      "contrastPriceInfo": {
      "contrastPrice": "248",
      "priceType": 4
      },
      "labelListWithStyle": [
      {
      "styleCode": 202,
      "content": "特价"
      },
      {
      "styleCode": 300,
      "content": "包税"
      }
      ],
      "enjoyPriceInfo": {
      "enjoyPrice": "289",
      "priceType": 0
      },
      "countryName": "兰蔻",
      "template": {
      "name": "kl_feed_goods",
      "version": "7",
      "url": "https://ossgw.alicdn.com/rapid-oss-bucket/1599199439687/kl_feed_goods.zip"
      },
      "goodsId": 279619,
      "categoryName": "化妆水/爽肤水",
      "imageUrl": "http://kaola-haitao.oss.kaolacdn.com/91f78e97c50b4d7d8d1c62cfc2c771f31556072739743juulj6a110397.jpg",
      "trackInfo": {
      "utScm": "20140737.p_279619.234618_234266_91519.cate_112044-cts_1599708057071-channel_2-fccrowds_ul-bucketid_null-contenttype_1-matchscore_4534-pvid_0c2824d7#9ffe#4dc2#bcdf#0d92c6f7f54c-price_2890000-pageno_1-appid_18806-matchtype_21-triggerweight_null-position_15-brand_1452-expid_null",
      "utLogMap": {
      "sr_price": "289.0",
      "sr_abid": "183397",
      "sr_trigger": "null",
      "sr_brand": "1452",
      "sr_pos": "15",
      "sr_appid": "18806",
      "sr_rank_score": "null",
      "mtx_exp": "null",
      "sr_cvr": "null",
      "sr_ctt_type": "null",
      "sr_match_type": "21",
      "sr_recall_score": "null",
      "mtx_crowds": "null",
      "sr_t_at": "null",
      "sr_object_type": "p",
      "sr_t_td": "null",
      "sr_scene": "2",
      "sr_match_score": "0.4534",
      "sr_pvid": "0c2824d7#9ffe#4dc2#bcdf#0d92c6f7f54c",
      "mtx_bucket": "null",
      "sr_object_id": "279619",
      "sr_ctt_goods": "null",
      "sr_pageno": "1",
      "sr_trigger_w": "null",
      "sr_cate": "112044",
      "sr_ctr": "null",
      "sr_tc_ctr": "null",
      "sr_final_score": "null",
      "sr_tc_clk": "null",
      "sr_tc_td": "null",
      "sr_pinleici": "爽肤水"
      }
      },
      "currentPrice": 289.00,
      "vip" :268,
      "similarLinkUrl": "http://m.kaola.com/klapp?klpn=similarGoodsPage&goods_id=279619",
      "showFeed": false
      },
      {
      "recType": 22,
      "countryLogo": "http://kaola-haitao.oss.kaolacdn.com/1077833fa2854dcb97502084f24f449d1419659976324i46kw8bh10001.png",
      "linkUrl": "https://m-goods.kaola.com/product/8641154.html",
      "goodsImage1":"https://kaola-pop.oss.kaolacdn.com/efe6d2c3dd46407c96b5e589f217deb6_800_800.jpg",
      "goodsImage": "http://kaola-haitao.oss.kaolacdn.com/363c6ee17f8846c387ff8ea300271bc8_800_800.jpg",
      "scm": "v1.1008.1008_p_8641154.234618_234266_91519.cate_736-cts_1599708057071-channel_2-fccrowds_ul-pinleici_-match&udl;score_0&doot;4393-bucketid_null-abid_183397-trigger&udl;weight_null-content&udl;type_1-pvid_0c2824d7#9ffe#4dc2#bcdf#0d92c6f7f54c-price_99&doot;0-pageno_1-appid_18806-match&udl;type_21-position_16-brand_4291-expid_null",
      "goodsName": "【教师节礼物】【特价包税多",
      "goodMinName":"色可选】MAC 魅可 子弹头系列时尚唇膏口红 3克 chili小辣椒 646脏橘色",
      "realTimeRec": false,
      "titleForeHeadLabelList": [

      ],
      "contrastPriceInfo": {
      "contrastPrice": "94",
      "priceType": 4
      },
      "labelListWithStyle": [
      {
      "styleCode": 201,
      "content": "每满300减30"
      },
      {
      "styleCode": 300,
      "content": "包税"
      }
      ],
      "enjoyPriceInfo": {
      "enjoyPrice": "99",
      "priceType": 0
      },
      "countryName": "魅可",
      "template": {
      "name": "kl_feed_goods",
      "version": "7",
      "url": "https://ossgw.alicdn.com/rapid-oss-bucket/1599199439687/kl_feed_goods.zip"
      },
      "goodsId": 8641154,
      "categoryName": "唇膏/口红",
      "imageUrl": "http://kaola-pop.oss.kaolacdn.com/5810ea747f2f4362aa45cc17112a8c27_800_800.jpg",
      "trackInfo": {
      "utScm": "20140737.p_8641154.234618_234266_91519.cate_736-cts_1599708057071-channel_2-fccrowds_ul-bucketid_null-contenttype_1-matchscore_4393-pvid_0c2824d7#9ffe#4dc2#bcdf#0d92c6f7f54c-price_990000-pageno_1-appid_18806-matchtype_21-triggerweight_null-position_16-brand_4291-expid_null",
      "utLogMap": {
      "sr_price": "99.0",
      "sr_abid": "183397",
      "sr_trigger": "null",
      "sr_brand": "4291",
      "sr_pos": "16",
      "sr_appid": "18806",
      "sr_rank_score": "null",
      "mtx_exp": "null",
      "sr_cvr": "null",
      "sr_ctt_type": "null",
      "sr_match_type": "21",
      "sr_recall_score": "null",
      "mtx_crowds": "null",
      "sr_t_at": "null",
      "sr_object_type": "p",
      "sr_t_td": "null",
      "sr_scene": "2",
      "sr_match_score": "0.4393",
      "sr_pvid": "0c2824d7#9ffe#4dc2#bcdf#0d92c6f7f54c",
      "mtx_bucket": "null",
      "sr_object_id": "8641154",
      "sr_ctt_goods": "null",
      "sr_pageno": "1",
      "sr_trigger_w": "null",
      "sr_cate": "736",
      "sr_ctr": "null",
      "sr_tc_ctr": "null",
      "sr_final_score": "null",
      "sr_tc_clk": "null",
      "sr_tc_td": "null",
      "sr_pinleici": ""
      }
      },
      "currentPrice": 99,
      "vip" :88,
      "similarLinkUrl": "http://m.kaola.com/klapp?klpn=similarGoodsPage&goods_id=8641154",
      "showFeed": false
      },
      {
      "recType": 22,
      "countryLogo": "http://kaola-haitao.oss.kaolacdn.com/1cc2m9est21_46_46.png",
      "linkUrl": "https://m-goods.kaola.com/product/1330333.html",
      "goodsImage1":"https://kaola-haitao.oss.kaolacdn.com/f255d93bb6ec4992b3bbacb3c0206d3f15998209606548A6C9E4BB22753286440030E5CC27D14.jpg?x-oss-process=image/resize,w_262,h_262/quality,q_90",
      "goodsImage": "http://kaola-haitao.oss.kaolacdn.com/641f1be9b76b4c9e9538a72f82d1f29a_800_800.jpg",
      "scm": "v1.1008.1008_p_1330333.234618_234266_91519.cate_547-cts_1599708057071-channel_2-fccrowds_ul-pinleici_洗面霜-match&udl;score_0&doot;3965-bucketid_null-abid_183397-trigger&udl;weight_null-content&udl;type_1-pvid_0c2824d7#9ffe#4dc2#bcdf#0d92c6f7f54c-price_119&doot;0-pageno_1-appid_18806-match&udl;type_21-position_17-brand_3230-expid_null",
      "goodsName": "Freeplus 芙丽芳丝 净润洗面",
      "goodMinName":"霜100克 氨基酸洗面奶男女 洁面乳日本",
      "realTimeRec": false,
      "titleForeHeadLabelList": [
      "https://kaola-haitao.oss.kaolacdn.com/e37aaf47-b4e4-4602-8309-5edf8a2300f8T2008031346_78_39.png?klsize=78x39"
      ],
      "contrastPriceInfo": {
      "contrastPrice": "109",
      "priceType": 4
      },
      "labelListWithStyle": [
      {
      "styleCode": 202,
      "content": "满299元领赠品"
      },
      {
      "styleCode": 202,
      "content": "豆抵1元"
      }
      ],
      "enjoyPriceInfo": {
      "enjoyPrice": "119",
      "priceType": 0
      },
      "countryName": "芙丽芳丝",
      "template": {
      "name": "kl_feed_goods",
      "version": "7",
      "url": "https://ossgw.alicdn.com/rapid-oss-bucket/1599199439687/kl_feed_goods.zip"
      },
      "goodsId": 1330333,
      "categoryName": "洁面",
      "imageUrl": "http://kaola-haitao.oss.kaolacdn.com/290b4de6a31043b3b56c61bb9735ef701587890164287D9BE4D8742A5875CC48B3668872DA203.jpg",
      "trackInfo": {
      "utScm": "20140737.p_1330333.234618_234266_91519.cate_547-cts_1599708057071-channel_2-fccrowds_ul-bucketid_null-contenttype_1-matchscore_3965-pvid_0c2824d7#9ffe#4dc2#bcdf#0d92c6f7f54c-price_1190000-pageno_1-appid_18806-matchtype_21-triggerweight_null-position_17-brand_3230-expid_null",
      "utLogMap": {
      "sr_price": "119.0",
      "sr_abid": "183397",
      "sr_trigger": "null",
      "sr_brand": "3230",
      "sr_pos": "17",
      "sr_appid": "18806",
      "sr_rank_score": "null",
      "mtx_exp": "null",
      "sr_cvr": "null",
      "sr_ctt_type": "null",
      "sr_match_type": "21",
      "sr_recall_score": "null",
      "mtx_crowds": "null",
      "sr_t_at": "null",
      "sr_object_type": "p",
      "sr_t_td": "null",
      "sr_scene": "2",
      "sr_match_score": "0.3965",
      "sr_pvid": "0c2824d7#9ffe#4dc2#bcdf#0d92c6f7f54c",
      "mtx_bucket": "null",
      "sr_object_id": "1330333",
      "sr_ctt_goods": "null",
      "sr_pageno": "1",
      "sr_trigger_w": "null",
      "sr_cate": "547",
      "sr_ctr": "null",
      "sr_tc_ctr": "null",
      "sr_final_score": "null",
      "sr_tc_clk": "null",
      "sr_tc_td": "null",
      "sr_pinleici": "洗面霜"
      }
      },
      "currentPrice": 119.00,
      "vip" :108,
      "similarLinkUrl": "http://m.kaola.com/klapp?klpn=similarGoodsPage&goods_id=1330333",
      "showFeed": false
      },
      {
      "recType": 22,
      "countryLogo": "http://kaola-haitao.oss.kaolacdn.com/7489e52daa45487c959de15a903495fb1419662677354i46mi4ix10009.png",
      "linkUrl": "https://m-goods.kaola.com/product/8229842.html",
      "goodsImage1":"https://kaola-pop.oss.kaolacdn.com/8fa323ee9907422f99ba4ea10b7a20df_800_800.jpg?x-oss-process=image/resize,w_262,h_262/quality,q_90",
      "goodsImage": "http://kaola-pop.oss.kaolacdn.com/f13970cc977142babfd59cc6c29d054e_800_800.jpg",
      "scm": "v1.1008.1008_p_8229842.234618_234266_91519.cate_112047-cts_1599708057071-channel_2-fccrowds_ul-pinleici_-match&udl;score_0&doot;3886-bucketid_null-abid_183397-trigger&udl;weight_null-content&udl;type_1-pvid_0c2824d7#9ffe#4dc2#bcdf#0d92c6f7f54c-price_69&doot;0-pageno_1-appid_18806-match&udl;type_21-position_18-brand_17680-expid_null",
      "goodsName": "【拼团50元】【毛孔吸尘",
      "goodMinName":"器】新西兰Geoskincare 纽西之谜火山岩泥清洁泥膜 深层去黑头收缩毛孔补水保湿涂抹式面膜 100ml",
      "realTimeRec": false,
      "titleForeHeadLabelList": [

      ],
      "contrastPriceInfo": {
      "contrastPrice": "59",
      "priceType": 4
      },
      "labelListWithStyle": [
      {
      "styleCode": 202,
      "content": "满2件减10"
      },
      {
      "styleCode": 201,
      "content": "5元"
      }
      ],
      "enjoyPriceInfo": {
      "enjoyPrice": "69",
      "priceType": 0
      },
      "countryName": "纽西之谜",
      "template": {
      "name": "kl_feed_goods",
      "version": "7",
      "url": "https://ossgw.alicdn.com/rapid-oss-bucket/1599199439687/kl_feed_goods.zip"
      },
      "goodsId": 8229842,
      "categoryName": "涂抹面膜",
      "imageUrl": "http://kaola-pop.oss.kaolacdn.com/f13970cc977142babfd59cc6c29d054e_800_800.jpg",
      "trackInfo": {
      "utScm": "20140737.p_8229842.234618_234266_91519.cate_112047-cts_1599708057071-channel_2-fccrowds_ul-bucketid_null-contenttype_1-matchscore_3886-pvid_0c2824d7#9ffe#4dc2#bcdf#0d92c6f7f54c-price_690000-pageno_1-appid_18806-matchtype_21-triggerweight_null-position_18-brand_17680-expid_null",
      "utLogMap": {
      "sr_price": "69.0",
      "sr_abid": "183397",
      "sr_trigger": "null",
      "sr_brand": "17680",
      "sr_pos": "18",
      "sr_appid": "18806",
      "sr_rank_score": "null",
      "mtx_exp": "null",
      "sr_cvr": "null",
      "sr_ctt_type": "null",
      "sr_match_type": "21",
      "sr_recall_score": "null",
      "mtx_crowds": "null",
      "sr_t_at": "null",
      "sr_object_type": "p",
      "sr_t_td": "null",
      "sr_scene": "2",
      "sr_match_score": "0.3886",
      "sr_pvid": "0c2824d7#9ffe#4dc2#bcdf#0d92c6f7f54c",
      "mtx_bucket": "null",
      "sr_object_id": "8229842",
      "sr_ctt_goods": "null",
      "sr_pageno": "1",
      "sr_trigger_w": "null",
      "sr_cate": "112047",
      "sr_ctr": "null",
      "sr_tc_ctr": "null",
      "sr_final_score": "null",
      "sr_tc_clk": "null",
      "sr_tc_td": "null",
      "sr_pinleici": ""
      }
      },
      "currentPrice": 69.00,
      "vip" :58,
      "similarLinkUrl": "http://m.kaola.com/klapp?klpn=similarGoodsPage&goods_id=8229842",
      "showFeed": false
      },
      {
         "recType": 22,
         "countryLogo": "http://kaola-haitao.oss.kaolacdn.com/d3c18d60f0e54c32af5cf24d18be585b1419662519909i46mer1g10007.png",
         "linkUrl": "https://m-goods.kaola.com/product/279619.html",
         "goodsImage1":"https://kaola-pop.oss.kaolacdn.com/0550986b9ea048bb8bff889419965388_800_800.jpg?x-oss-process=image/resize,w_262,h_262/quality,q_90",
         "goodsImage": "http://kaola-haitao.oss.kaolacdn.com/05a74754645844fd808db831a1150d68_800_800.jpg",
         "scm": "v1.1008.1008_p_279619.234618_234266_91519.cate_112044-cts_1599708057071-channel_2-fccrowds_ul-pinleici_爽肤水-match&udl;score_0&doot;4534-bucketid_null-abid_183397-trigger&udl;weight_null-content&udl;type_1-pvid_0c2824d7#9ffe#4dc2#bcdf#0d92c6f7f54c-price_289&doot;0-pageno_1-appid_18806-match&udl;type_21-position_15-brand_1452-expid_null",
         "goodsName": "LANCÔME 兰蔻 玫瑰露清滢",
         "goodMinName":"柔肤粉水 400毫升 干皮真爱",
         "realTimeRec": false,
         "titleForeHeadLabelList": [
         "https://kaola-haitao.oss.kaolacdn.com/e37aaf47-b4e4-4602-8309-5edf8a2300f8T2008031346_78_39.png?klsize=78x39"
         ],
         "contrastPriceInfo": {
         "contrastPrice": "248",
         "priceType": 4
         },
         "labelListWithStyle": [
         {
         "styleCode": 202,
         "content": "特价"
         },
         {
         "styleCode": 300,
         "content": "包税"
         }
         ],
         "enjoyPriceInfo": {
         "enjoyPrice": "289",
         "priceType": 0
         },
         "countryName": "兰蔻",
         "template": {
         "name": "kl_feed_goods",
         "version": "7",
         "url": "https://ossgw.alicdn.com/rapid-oss-bucket/1599199439687/kl_feed_goods.zip"
         },
         "goodsId": 279619,
         "categoryName": "化妆水/爽肤水",
         "imageUrl": "http://kaola-haitao.oss.kaolacdn.com/91f78e97c50b4d7d8d1c62cfc2c771f31556072739743juulj6a110397.jpg",
         "trackInfo": {
         "utScm": "20140737.p_279619.234618_234266_91519.cate_112044-cts_1599708057071-channel_2-fccrowds_ul-bucketid_null-contenttype_1-matchscore_4534-pvid_0c2824d7#9ffe#4dc2#bcdf#0d92c6f7f54c-price_2890000-pageno_1-appid_18806-matchtype_21-triggerweight_null-position_15-brand_1452-expid_null",
         "utLogMap": {
         "sr_price": "289.0",
         "sr_abid": "183397",
         "sr_trigger": "null",
         "sr_brand": "1452",
         "sr_pos": "15",
         "sr_appid": "18806",
         "sr_rank_score": "null",
         "mtx_exp": "null",
         "sr_cvr": "null",
         "sr_ctt_type": "null",
         "sr_match_type": "21",
         "sr_recall_score": "null",
         "mtx_crowds": "null",
         "sr_t_at": "null",
         "sr_object_type": "p",
         "sr_t_td": "null",
         "sr_scene": "2",
         "sr_match_score": "0.4534",
         "sr_pvid": "0c2824d7#9ffe#4dc2#bcdf#0d92c6f7f54c",
         "mtx_bucket": "null",
         "sr_object_id": "279619",
         "sr_ctt_goods": "null",
         "sr_pageno": "1",
         "sr_trigger_w": "null",
         "sr_cate": "112044",
         "sr_ctr": "null",
         "sr_tc_ctr": "null",
         "sr_final_score": "null",
         "sr_tc_clk": "null",
         "sr_tc_td": "null",
         "sr_pinleici": "爽肤水"
         }
         },
         "currentPrice": 289.00,
         "vip" :268,
         "similarLinkUrl": "http://m.kaola.com/klapp?klpn=similarGoodsPage&goods_id=279619",
         "showFeed": false
         } 
      ],
      "classifyList":[
         {
            "img":"https://kaola-haitao.oss.kaolacdn.com/9b025db966cc4ecea102913da33f88091532519165980jk12ccg812567.jpg?x-oss-process=image/resize,w_240,h_240/quality,q_75/format,webp",
            "name":"口红"
         },
         {
            "img":"https://kaola-haitao.oss.kaolacdn.com/a9dc57196224482682d5066e4e69a6af1530779626254jj8anz0112321.jpg?x-oss-process=image/resize,w_240,h_240/quality,q_75/format,webp",
            "name":"面膜"
         },
         {
            "img":"https://kaola-haitao.oss.kaolacdn.com/jpux5w3273null.jpg?x-oss-process=image/resize,w_240,h_240/quality,q_75/format,webp",
            "name":"面膜大赏"
         },
         {
            "img":"https://kaola-haitao.oss.kaolacdn.com/06c2130ab9b048d39d144480764ee75d1525850606881jgys1zbe11840.jpg?x-oss-process=image/resize,w_240,h_240/quality,q_75/format,webp",
            "name":"防晒"
         },
         {
            "img":"https://kaola-haitao.oss.kaolacdn.com/imq35qx294_800_800.jpg?x-oss-process=image/resize,w_240,h_240/quality,q_75/format,webp",
            "name":"洗面奶"
         },
         {
            "img":"https://kaola-haitao.oss.kaolacdn.com/c649ba4a75fd48fbbbd1742048c1476e1505377168674j7k6p5ak10027.jpg?x-oss-process=image/resize,w_240,h_240/quality,q_75/format,webp",
            "name":"眼霜"
         },
         {
            "img":"https://kaola-haitao.oss.kaolacdn.com/onlineih1cldcu11053.jpg?x-oss-process=image/resize,w_240,h_240/quality,q_75/format,webp",
            "name":"香水"
         },
         {
            "img":"https://kaola-haitao.oss.kaolacdn.com/izqyc2fj45_800_800.jpg?x-oss-process=image/resize,w_240,h_240/quality,q_75/format,webp",
            "name":"眼影"
         },
         {
            "img":"https://kaola-haitao.oss.kaolacdn.com/1blereva030_800_800.jpg?x-oss-process=image/resize,w_240,h_240/quality,q_75/format,webp",
            "name":"气垫"
         },
         {
            "img":"https://kaola-haitao.oss.kaolacdn.com/f192f2db1d2843509c155af9435c76641527242104530jhlsiloo10624.jpg?x-oss-process=image/resize,w_240,h_240/quality,q_75/format,webp",
            "name":"卸妆"
         },
         {
            "img":"https://kaola-haitao.oss.kaolacdn.com/jpux32bk71null.jpg?x-oss-process=image/resize,w_240,h_240/quality,q_75/format,webp",
            "name":"口红种草"
         }
      ],
      "classiftTwo":[
         {
            "img":"https://kaola-haitao.oss.kaolacdn.com/ipbyqbwy44_180_180.jpg?x-oss-process=image/resize,w_240,h_240/quality,q_75/format,webp",
            "name":"面部清洁"
         },
         {
            "img":"https://kaola-haitao.oss.kaolacdn.com/ipbyql7q47_180_180.jpg?x-oss-process=image/resize,w_240,h_240/quality,q_75/format,webp",
            "name":"化妆水"
         },
         {
            "img":"https://kaola-haitao.oss.kaolacdn.com/ipbyqpqd46_180_180.jpg?x-oss-process=image/resize,w_240,h_240/quality,q_75/format,webp",
            "name":"面膜"
         },
         {
            "img":"https://kaola-haitao.oss.kaolacdn.com/ipbyqut060_180_180.jpg?x-oss-process=image/resize,w_240,h_240/quality,q_75/format,webp",
            "name":"面霜"
         },
         {
            "img":"https://kaola-haitao.oss.kaolacdn.com/ipbyr0007_180_180.jpg?x-oss-process=image/resize,w_240,h_240/quality,q_75/format,webp",
            "name":"乳液"
         },
         {
            "img":"https://kaola-haitao.oss.kaolacdn.com/ipbyr50q5_180_180.jpg?x-oss-process=image/resize,w_240,h_240/quality,q_75/format,webp",
            "name":"喷雾"
         },
         {
            "img":"https://kaola-haitao.oss.kaolacdn.com/ipbyrauc32_180_180.jpg?x-oss-process=image/resize,w_240,h_240/quality,q_75/format,webp",
            "name":"面部精华"
         },
         {
            "img":"https://kaola-haitao.oss.kaolacdn.com/ipbyrg5145_180_180.jpg?x-oss-process=image/resize,w_240,h_240/quality,q_75/format,webp",
            "name":"唇部护理"
         },
         {
            "img":"https://kaola-haitao.oss.kaolacdn.com/ipcdnbld0_180_180.jpg?x-oss-process=image/resize,w_240,h_240/quality,q_75/format,webp",
            "name":"防晒修复"
         }
      ],
      "product":[
         {
            "img":"https://kaola-haitao.oss.kaolacdn.com/jw237njq20null.jpg?x-oss-process=image/resize,w_240,h_240/quality,q_75/format,webp",
            "name":"家有萌宝"
         },
         {
            "img":"https://kaola-haitao.oss.kaolacdn.com/1c12o2h4p60_400_400.jpg?x-oss-process=image/resize,w_240,h_240/quality,q_75/format,webp",
            "name":"母婴正品"
         },
          {
            "img":"https://kaola-haitao.oss.kaolacdn.com/1c12o40mh5_400_400.jpg?x-oss-process=image/resize,w_240,h_240/quality,q_75/format,webp",
            "name":"尤妮佳"
         },
         {
            "img":"https://kaola-haitao.oss.kaolacdn.com/1c12o4s0d36_400_400.jpg?x-oss-process=image/resize,w_240,h_240/quality,q_75/format,webp",
            "name":"爱他美(德国)"
         },
         {
            "img":"https://kaola-haitao.oss.kaolacdn.com/1c12o616d31_400_400.jpg?x-oss-process=image/resize,w_240,h_240/quality,q_75/format,webp",
            "name":"a2"
         },
         {
            "img":"https://kaola-haitao.oss.kaolacdn.com/1c12oe0tb75_400_400.jpg?x-oss-process=image/resize,w_240,h_240/quality,q_75/format,webp",
            "name":"贝拉米"
         },
         {
            "img":"https://kaola-haitao.oss.kaolacdn.com/116d2f05f63248e2a15f508dd2c1d4b41516279053526jckhedha10187.jpg?x-oss-process=image/resize,w_240,h_240/quality,q_75/format,webp",
            "name":"帮宝适"
         },
         {
            "img":"https://kaola-haitao.oss.kaolacdn.com/1c12oclef68_400_400.jpg?x-oss-process=image/resize,w_240,h_240/quality,q_75/format,webp",
            "name":"喜宝"
         }
      ]
}